believe/__init__.py
believe/dict_matcher.py
believe/error.py
believe/internal.py
believe/list_matcher.py
believe/number_matcher.py
believe/other_matcher.py
believe/str_matcher.py
believe-1.0.14.dist-info/LICENSE
believe-1.0.14.dist-info/WHEEL
believe-1.0.14.dist-info/METADATA
believe-1.0.14.dist-info/RECORD
