Metadata-Version: 2.1
Name: believe
Version: 1.0.14
Summary: A easy to use validator for json content
Keywords: json,validate,validator
Author-email: Seth Wang <pkyosx@gmail.com>
Requires-Python: >=3.6
Classifier: License :: OSI Approved :: MIT License
Classifier: Operating System :: OS Independent
Classifier: Programming Language :: Python :: 3
Classifier: Programming Language :: Python :: 3.8
Classifier: Programming Language :: Python :: 3.9
Classifier: Programming Language :: Python :: 3.10
Classifier: Programming Language :: Python :: 3.11
Classifier: Programming Language :: Python :: 3.12
Requires-Dist: flit ; extra == "publish"
Requires-Dist: coverage<7.0.0 ; extra == "test"
Requires-Dist: pytest ; extra == "test"
Requires-Dist: pytest-cov ; extra == "test"
Requires-Dist: coverage-lcov ; extra == "test"
Requires-Dist: toml ; extra == "test"
Project-URL: Home, https://github.com/pkyosx/believe
Provides-Extra: publish
Provides-Extra: test
